napari_ome_arrow/__init__.py
napari_ome_arrow/_reader.py
napari_ome_arrow/_version.py
napari_ome_arrow/napari.yaml
napari_ome_arrow-0.0.2.dist-info/licenses/LICENSE
napari_ome_arrow-0.0.2.dist-info/METADATA
napari_ome_arrow-0.0.2.dist-info/WHEEL
napari_ome_arrow-0.0.2.dist-info/entry_points.txt
napari_ome_arrow-0.0.2.dist-info/top_level.txt
napari_ome_arrow-0.0.2.dist-info/RECORD
