Metadata-Version: 2.4
Name: napari-ome-arrow
Version: 0.0.2
Summary: A Napari plugin for OME-Arrow and OME-Parquet bioimage data
License: 
Project-URL: Bug Tracker, https://github.com/wayscience/napari-ome-arrow/issues
Project-URL: Documentation, https://github.com/wayscience/napari-ome-arrow#README.md
Project-URL: Source Code, https://github.com/wayscience/napari-ome-arrow
Project-URL: User Support, https://github.com/wayscience/napari-ome-arrow/issues
Classifier: Framework :: napari
Classifier: Intended Audience :: Developers
Classifier: License :: OSI Approved :: BSD License
Classifier: Operating System :: OS Independent
Classifier: Programming Language :: Python
Classifier: Programming Language :: Python :: 3 :: Only
Classifier: Programming Language :: Python :: 3.11
Classifier: Programming Language :: Python :: 3.12
Classifier: Programming Language :: Python :: 3.13
Classifier: Programming Language :: Python :: 3.14
Classifier: Topic :: Scientific/Engineering :: Image Processing
Requires-Python: >=3.11
License-File: LICENSE
Requires-Dist: magicgui
Requires-Dist: numpy
Requires-Dist: ome-arrow>=0.0.2
Requires-Dist: qtpy>=2.4
Requires-Dist: scikit-image
Provides-Extra: all
Requires-Dist: napari; extra == "all"
Requires-Dist: qtpy>=2.4; extra == "all"
Provides-Extra: pyqt6
Requires-Dist: napari[pyqt6]; extra == "pyqt6"
Requires-Dist: pyqt6>=6.6; extra == "pyqt6"
Requires-Dist: qtpy>=2.4; extra == "pyqt6"
Provides-Extra: pyside6
Requires-Dist: napari[pyside6]; extra == "pyside6"
Requires-Dist: pyside6>=6.6; extra == "pyside6"
Requires-Dist: qtpy>=2.4; extra == "pyside6"
Dynamic: license-file
